Metadata-Version: 2.1
Name: format-BRL
Version: 0.0.1
Summary: Oficial
Author: Icaro Rubem
Author-email: icarorubem63@gmail.com
License: MIT License
Keywords: BRL_CONVERSOR
License-File: LICENCE
